<?xml version="1.0" encoding="utf-8"?>
<REH issuedAt="18UTC 05 Jan 2017" basedOn=" ">
 <regionGroup grCode="8318" grName="주요 지점">
  <stn stnName="알펜시아-스키점프-착지" stnNo="2575">
   <dataSet lst="0604" val="94.2" />
   <dataSet lst="0605" val="96.7" />
   <dataSet lst="0606" val="96.8" />
   <dataSet lst="0607" val="96.0" />
   <dataSet lst="0608" val="96.6" />
   <dataSet lst="0609" val="92.3" />
   <dataSet lst="0610" val="85.9" />
   <dataSet lst="0611" val="78.9" />
   <dataSet lst="0612" val="70.1" />
   <dataSet lst="0613" val="64.4" />
   <dataSet lst="0614" val="58.1" />
   <dataSet lst="0615" val="59.8" />
   <dataSet lst="0616" val="64.1" />
   <dataSet lst="0617" val="74.9" />
   <dataSet lst="0618" val="78.9" />
   <dataSet lst="0619" val="85.8" />
   <dataSet lst="0620" val="88.4" />
   <dataSet lst="0621" val="90.1" />
   <dataSet lst="0622" val="87.5" />
   <dataSet lst="0623" val="89.1" />
   <dataSet lst="0700" val="87.3" />
   <dataSet lst="0701" val="87.8" />
   <dataSet lst="0702" val="89.8" />
   <dataSet lst="0703" val="89.7" />
  </stn>
  <stn stnName="용평-알파인-대회전-도착" stnNo="2561">
   <dataSet lst="0604" val="98.7" />
   <dataSet lst="0605" val="99.6" />
   <dataSet lst="0606" val="99.5" />
   <dataSet lst="0607" val="100.0" />
   <dataSet lst="0608" val="100.0" />
   <dataSet lst="0609" val="94.4" />
   <dataSet lst="0610" val="85.7" />
   <dataSet lst="0611" val="80.6" />
   <dataSet lst="0612" val="73.2" />
   <dataSet lst="0613" val="68.9" />
   <dataSet lst="0614" val="58.2" />
   <dataSet lst="0615" val="63.4" />
   <dataSet lst="0616" val="65.0" />
   <dataSet lst="0617" val="77.2" />
   <dataSet lst="0618" val="81.6" />
   <dataSet lst="0619" val="90.3" />
   <dataSet lst="0620" val="90.3" />
   <dataSet lst="0621" val="88.6" />
   <dataSet lst="0622" val="86.1" />
   <dataSet lst="0623" val="85.9" />
   <dataSet lst="0700" val="86.8" />
   <dataSet lst="0701" val="88.9" />
   <dataSet lst="0702" val="90.0" />
   <dataSet lst="0703" val="86.9" />
  </stn>
  <stn stnName="보광-크로스-도착" stnNo="2581">
   <dataSet lst="0604" val="99.1" />
   <dataSet lst="0605" val="96.5" />
   <dataSet lst="0606" val="96.6" />
   <dataSet lst="0607" val="99.2" />
   <dataSet lst="0608" val="99.9" />
   <dataSet lst="0609" val="95.3" />
   <dataSet lst="0610" val="85.7" />
   <dataSet lst="0611" val="74.9" />
   <dataSet lst="0612" val="68.5" />
   <dataSet lst="0613" val="68.6" />
   <dataSet lst="0614" val="66.5" />
   <dataSet lst="0615" val="68.5" />
   <dataSet lst="0616" val="74.5" />
   <dataSet lst="0617" val="82.5" />
   <dataSet lst="0618" val="77.5" />
   <dataSet lst="0619" val="79.2" />
   <dataSet lst="0620" val="87.6" />
   <dataSet lst="0621" val="87.2" />
   <dataSet lst="0622" val="91.6" />
   <dataSet lst="0623" val="89.0" />
   <dataSet lst="0700" val="95.2" />
   <dataSet lst="0701" val="99.6" />
   <dataSet lst="0702" val="100.0" />
   <dataSet lst="0703" val="93.0" />
  </stn>
  <stn stnName="정선-알파인-활강-도착" stnNo="2587">
   <dataSet lst="0604" val="93.0" />
   <dataSet lst="0605" val="89.4" />
   <dataSet lst="0606" val="94.4" />
   <dataSet lst="0607" val="95.3" />
   <dataSet lst="0608" val="95.3" />
   <dataSet lst="0609" val="88.6" />
   <dataSet lst="0610" val="79.1" />
   <dataSet lst="0611" val="68.9" />
   <dataSet lst="0612" val="67.7" />
   <dataSet lst="0613" val="66.8" />
   <dataSet lst="0614" val="65.9" />
   <dataSet lst="0615" val="64.5" />
   <dataSet lst="0616" val="72.7" />
   <dataSet lst="0617" val="73.7" />
   <dataSet lst="0618" val="71.4" />
   <dataSet lst="0619" val="74.0" />
   <dataSet lst="0620" val="77.8" />
   <dataSet lst="0621" val="86.2" />
   <dataSet lst="0622" val="86.5" />
   <dataSet lst="0623" val="88.7" />
   <dataSet lst="0700" val="87.1" />
   <dataSet lst="0701" val="89.6" />
   <dataSet lst="0702" val="89.3" />
   <dataSet lst="0703" val="89.7" />
  </stn>
  <stn stnName="강릉" stnNo="47105">
   <dataSet lst="0604" val="91.1" />
   <dataSet lst="0605" val="89.9" />
   <dataSet lst="0606" val="90.6" />
   <dataSet lst="0607" val="88.0" />
   <dataSet lst="0608" val="85.5" />
   <dataSet lst="0609" val="81.6" />
   <dataSet lst="0610" val="76.0" />
   <dataSet lst="0611" val="68.8" />
   <dataSet lst="0612" val="67.2" />
   <dataSet lst="0613" val="63.1" />
   <dataSet lst="0614" val="60.8" />
   <dataSet lst="0615" val="61.5" />
   <dataSet lst="0616" val="67.3" />
   <dataSet lst="0617" val="83.0" />
   <dataSet lst="0618" val="83.7" />
   <dataSet lst="0619" val="74.2" />
   <dataSet lst="0620" val="72.0" />
   <dataSet lst="0621" val="70.9" />
   <dataSet lst="0622" val="67.2" />
   <dataSet lst="0623" val="64.4" />
   <dataSet lst="0700" val="61.6" />
   <dataSet lst="0701" val="61.0" />
   <dataSet lst="0702" val="60.4" />
   <dataSet lst="0703" val="61.5" />
  </stn>
 </regionGroup>
 <regionGroup grCode="9901" grName="알펜시아 센터(스키점프)">
  <stn stnName="스키점프-K125-출발" stnNo="2572">
   <dataSet lst="0604" val="94.2" />
   <dataSet lst="0605" val="96.7" />
   <dataSet lst="0606" val="96.8" />
   <dataSet lst="0607" val="96.0" />
   <dataSet lst="0608" val="96.6" />
   <dataSet lst="0609" val="92.3" />
   <dataSet lst="0610" val="85.9" />
   <dataSet lst="0611" val="78.9" />
   <dataSet lst="0612" val="70.1" />
   <dataSet lst="0613" val="64.4" />
   <dataSet lst="0614" val="58.1" />
   <dataSet lst="0615" val="59.8" />
   <dataSet lst="0616" val="64.1" />
   <dataSet lst="0617" val="74.9" />
   <dataSet lst="0618" val="78.9" />
   <dataSet lst="0619" val="85.8" />
   <dataSet lst="0620" val="88.4" />
   <dataSet lst="0621" val="90.1" />
   <dataSet lst="0622" val="87.5" />
   <dataSet lst="0623" val="89.1" />
   <dataSet lst="0700" val="87.3" />
   <dataSet lst="0701" val="87.8" />
   <dataSet lst="0702" val="89.8" />
   <dataSet lst="0703" val="89.7" />
  </stn>
  <stn stnName="스키점프-K125-점프" stnNo="2555">
   <dataSet lst="0604" val="94.2" />
   <dataSet lst="0605" val="96.7" />
   <dataSet lst="0606" val="96.8" />
   <dataSet lst="0607" val="96.0" />
   <dataSet lst="0608" val="96.6" />
   <dataSet lst="0609" val="92.3" />
   <dataSet lst="0610" val="85.9" />
   <dataSet lst="0611" val="78.9" />
   <dataSet lst="0612" val="70.1" />
   <dataSet lst="0613" val="64.4" />
   <dataSet lst="0614" val="58.1" />
   <dataSet lst="0615" val="59.8" />
   <dataSet lst="0616" val="64.1" />
   <dataSet lst="0617" val="74.9" />
   <dataSet lst="0618" val="78.9" />
   <dataSet lst="0619" val="85.8" />
   <dataSet lst="0620" val="88.4" />
   <dataSet lst="0621" val="90.1" />
   <dataSet lst="0622" val="87.5" />
   <dataSet lst="0623" val="89.1" />
   <dataSet lst="0700" val="87.3" />
   <dataSet lst="0701" val="87.8" />
   <dataSet lst="0702" val="89.8" />
   <dataSet lst="0703" val="89.7" />
  </stn>
  <stn stnName="스키점프-K98-출발" stnNo="2573">
   <dataSet lst="0604" val="94.2" />
   <dataSet lst="0605" val="96.7" />
   <dataSet lst="0606" val="96.8" />
   <dataSet lst="0607" val="96.0" />
   <dataSet lst="0608" val="96.6" />
   <dataSet lst="0609" val="92.3" />
   <dataSet lst="0610" val="85.9" />
   <dataSet lst="0611" val="78.9" />
   <dataSet lst="0612" val="70.1" />
   <dataSet lst="0613" val="64.4" />
   <dataSet lst="0614" val="58.1" />
   <dataSet lst="0615" val="59.8" />
   <dataSet lst="0616" val="64.1" />
   <dataSet lst="0617" val="74.9" />
   <dataSet lst="0618" val="78.9" />
   <dataSet lst="0619" val="85.8" />
   <dataSet lst="0620" val="88.4" />
   <dataSet lst="0621" val="90.1" />
   <dataSet lst="0622" val="87.5" />
   <dataSet lst="0623" val="89.1" />
   <dataSet lst="0700" val="87.3" />
   <dataSet lst="0701" val="87.8" />
   <dataSet lst="0702" val="89.8" />
   <dataSet lst="0703" val="89.7" />
  </stn>
  <stn stnName="스키점프-K98점프" stnNo="2574">
   <dataSet lst="0604" val="94.2" />
   <dataSet lst="0605" val="96.7" />
   <dataSet lst="0606" val="96.8" />
   <dataSet lst="0607" val="96.0" />
   <dataSet lst="0608" val="96.6" />
   <dataSet lst="0609" val="92.3" />
   <dataSet lst="0610" val="85.9" />
   <dataSet lst="0611" val="78.9" />
   <dataSet lst="0612" val="70.1" />
   <dataSet lst="0613" val="64.4" />
   <dataSet lst="0614" val="58.1" />
   <dataSet lst="0615" val="59.8" />
   <dataSet lst="0616" val="64.1" />
   <dataSet lst="0617" val="74.9" />
   <dataSet lst="0618" val="78.9" />
   <dataSet lst="0619" val="85.8" />
   <dataSet lst="0620" val="88.4" />
   <dataSet lst="0621" val="90.1" />
   <dataSet lst="0622" val="87.5" />
   <dataSet lst="0623" val="89.1" />
   <dataSet lst="0700" val="87.3" />
   <dataSet lst="0701" val="87.8" />
   <dataSet lst="0702" val="89.8" />
   <dataSet lst="0703" val="89.7" />
  </stn>
  <stn stnName="스키점프-착지" stnNo="2575">
   <dataSet lst="0604" val="94.2" />
   <dataSet lst="0605" val="96.7" />
   <dataSet lst="0606" val="96.8" />
   <dataSet lst="0607" val="96.0" />
   <dataSet lst="0608" val="96.6" />
   <dataSet lst="0609" val="92.3" />
   <dataSet lst="0610" val="85.9" />
   <dataSet lst="0611" val="78.9" />
   <dataSet lst="0612" val="70.1" />
   <dataSet lst="0613" val="64.4" />
   <dataSet lst="0614" val="58.1" />
   <dataSet lst="0615" val="59.8" />
   <dataSet lst="0616" val="64.1" />
   <dataSet lst="0617" val="74.9" />
   <dataSet lst="0618" val="78.9" />
   <dataSet lst="0619" val="85.8" />
   <dataSet lst="0620" val="88.4" />
   <dataSet lst="0621" val="90.1" />
   <dataSet lst="0622" val="87.5" />
   <dataSet lst="0623" val="89.1" />
   <dataSet lst="0700" val="87.3" />
   <dataSet lst="0701" val="87.8" />
   <dataSet lst="0702" val="89.8" />
   <dataSet lst="0703" val="89.7" />
  </stn>
  <stn stnName="스키점프" stnNo="879">
   <dataSet lst="0604" val="94.2" />
   <dataSet lst="0605" val="96.7" />
   <dataSet lst="0606" val="96.8" />
   <dataSet lst="0607" val="96.0" />
   <dataSet lst="0608" val="96.6" />
   <dataSet lst="0609" val="92.3" />
   <dataSet lst="0610" val="85.9" />
   <dataSet lst="0611" val="78.9" />
   <dataSet lst="0612" val="70.1" />
   <dataSet lst="0613" val="64.4" />
   <dataSet lst="0614" val="58.1" />
   <dataSet lst="0615" val="59.8" />
   <dataSet lst="0616" val="64.1" />
   <dataSet lst="0617" val="74.9" />
   <dataSet lst="0618" val="78.9" />
   <dataSet lst="0619" val="85.8" />
   <dataSet lst="0620" val="88.4" />
   <dataSet lst="0621" val="90.1" />
   <dataSet lst="0622" val="87.5" />
   <dataSet lst="0623" val="89.1" />
   <dataSet lst="0700" val="87.3" />
   <dataSet lst="0701" val="87.8" />
   <dataSet lst="0702" val="89.8" />
   <dataSet lst="0703" val="89.7" />
  </stn>
 </regionGroup>
 <regionGroup grCode="9902" grName="알펜시아 센터(종합)">
  <stn stnName="바이애슬론-출발" stnNo="2557">
   <dataSet lst="0604" val="94.9" />
   <dataSet lst="0605" val="96.8" />
   <dataSet lst="0606" val="98.4" />
   <dataSet lst="0607" val="97.9" />
   <dataSet lst="0608" val="97.7" />
   <dataSet lst="0609" val="93.3" />
   <dataSet lst="0610" val="86.6" />
   <dataSet lst="0611" val="80.1" />
   <dataSet lst="0612" val="72.0" />
   <dataSet lst="0613" val="64.8" />
   <dataSet lst="0614" val="58.2" />
   <dataSet lst="0615" val="59.2" />
   <dataSet lst="0616" val="62.6" />
   <dataSet lst="0617" val="76.2" />
   <dataSet lst="0618" val="79.7" />
   <dataSet lst="0619" val="89.1" />
   <dataSet lst="0620" val="90.1" />
   <dataSet lst="0621" val="90.9" />
   <dataSet lst="0622" val="88.0" />
   <dataSet lst="0623" val="88.8" />
   <dataSet lst="0700" val="88.8" />
   <dataSet lst="0701" val="87.7" />
   <dataSet lst="0702" val="87.6" />
   <dataSet lst="0703" val="89.7" />
  </stn>
  <stn stnName="바이애슬론-중간" stnNo="2558">
   <dataSet lst="0604" val="94.9" />
   <dataSet lst="0605" val="96.8" />
   <dataSet lst="0606" val="98.4" />
   <dataSet lst="0607" val="97.9" />
   <dataSet lst="0608" val="97.7" />
   <dataSet lst="0609" val="93.3" />
   <dataSet lst="0610" val="86.6" />
   <dataSet lst="0611" val="80.1" />
   <dataSet lst="0612" val="72.0" />
   <dataSet lst="0613" val="64.8" />
   <dataSet lst="0614" val="58.2" />
   <dataSet lst="0615" val="59.2" />
   <dataSet lst="0616" val="62.6" />
   <dataSet lst="0617" val="76.2" />
   <dataSet lst="0618" val="79.7" />
   <dataSet lst="0619" val="89.1" />
   <dataSet lst="0620" val="90.1" />
   <dataSet lst="0621" val="90.9" />
   <dataSet lst="0622" val="88.0" />
   <dataSet lst="0623" val="88.8" />
   <dataSet lst="0700" val="88.8" />
   <dataSet lst="0701" val="87.7" />
   <dataSet lst="0702" val="87.6" />
   <dataSet lst="0703" val="89.7" />
  </stn>
  <stn stnName="크로스컨트리-출발" stnNo="2577">
   <dataSet lst="0604" val="94.9" />
   <dataSet lst="0605" val="96.8" />
   <dataSet lst="0606" val="98.4" />
   <dataSet lst="0607" val="97.9" />
   <dataSet lst="0608" val="97.7" />
   <dataSet lst="0609" val="93.3" />
   <dataSet lst="0610" val="86.6" />
   <dataSet lst="0611" val="80.1" />
   <dataSet lst="0612" val="72.0" />
   <dataSet lst="0613" val="64.8" />
   <dataSet lst="0614" val="58.2" />
   <dataSet lst="0615" val="59.2" />
   <dataSet lst="0616" val="62.6" />
   <dataSet lst="0617" val="76.2" />
   <dataSet lst="0618" val="79.7" />
   <dataSet lst="0619" val="89.1" />
   <dataSet lst="0620" val="90.1" />
   <dataSet lst="0621" val="90.9" />
   <dataSet lst="0622" val="88.0" />
   <dataSet lst="0623" val="88.8" />
   <dataSet lst="0700" val="88.8" />
   <dataSet lst="0701" val="87.7" />
   <dataSet lst="0702" val="87.6" />
   <dataSet lst="0703" val="89.7" />
  </stn>
  <stn stnName="크로스컨트리-중간" stnNo="2559">
   <dataSet lst="0604" val="94.2" />
   <dataSet lst="0605" val="96.7" />
   <dataSet lst="0606" val="96.8" />
   <dataSet lst="0607" val="96.0" />
   <dataSet lst="0608" val="96.6" />
   <dataSet lst="0609" val="92.3" />
   <dataSet lst="0610" val="85.9" />
   <dataSet lst="0611" val="78.9" />
   <dataSet lst="0612" val="70.1" />
   <dataSet lst="0613" val="64.4" />
   <dataSet lst="0614" val="58.1" />
   <dataSet lst="0615" val="59.8" />
   <dataSet lst="0616" val="64.1" />
   <dataSet lst="0617" val="74.9" />
   <dataSet lst="0618" val="78.9" />
   <dataSet lst="0619" val="85.8" />
   <dataSet lst="0620" val="88.4" />
   <dataSet lst="0621" val="90.1" />
   <dataSet lst="0622" val="87.5" />
   <dataSet lst="0623" val="89.1" />
   <dataSet lst="0700" val="87.3" />
   <dataSet lst="0701" val="87.8" />
   <dataSet lst="0702" val="89.8" />
   <dataSet lst="0703" val="89.7" />
  </stn>
  <stn stnName="슬라이딩-출발" stnNo="2553">
   <dataSet lst="0604" val="94.2" />
   <dataSet lst="0605" val="96.7" />
   <dataSet lst="0606" val="96.8" />
   <dataSet lst="0607" val="96.0" />
   <dataSet lst="0608" val="96.6" />
   <dataSet lst="0609" val="92.3" />
   <dataSet lst="0610" val="85.9" />
   <dataSet lst="0611" val="78.9" />
   <dataSet lst="0612" val="70.1" />
   <dataSet lst="0613" val="64.4" />
   <dataSet lst="0614" val="58.1" />
   <dataSet lst="0615" val="59.8" />
   <dataSet lst="0616" val="64.1" />
   <dataSet lst="0617" val="74.9" />
   <dataSet lst="0618" val="78.9" />
   <dataSet lst="0619" val="85.8" />
   <dataSet lst="0620" val="88.4" />
   <dataSet lst="0621" val="90.1" />
   <dataSet lst="0622" val="87.5" />
   <dataSet lst="0623" val="89.1" />
   <dataSet lst="0700" val="87.3" />
   <dataSet lst="0701" val="87.8" />
   <dataSet lst="0702" val="89.8" />
   <dataSet lst="0703" val="89.7" />
  </stn>
  <stn stnName="슬라이딩-중간" stnNo="2576">
   <dataSet lst="0604" val="94.2" />
   <dataSet lst="0605" val="96.7" />
   <dataSet lst="0606" val="96.8" />
   <dataSet lst="0607" val="96.0" />
   <dataSet lst="0608" val="96.6" />
   <dataSet lst="0609" val="92.3" />
   <dataSet lst="0610" val="85.9" />
   <dataSet lst="0611" val="78.9" />
   <dataSet lst="0612" val="70.1" />
   <dataSet lst="0613" val="64.4" />
   <dataSet lst="0614" val="58.1" />
   <dataSet lst="0615" val="59.8" />
   <dataSet lst="0616" val="64.1" />
   <dataSet lst="0617" val="74.9" />
   <dataSet lst="0618" val="78.9" />
   <dataSet lst="0619" val="85.8" />
   <dataSet lst="0620" val="88.4" />
   <dataSet lst="0621" val="90.1" />
   <dataSet lst="0622" val="87.5" />
   <dataSet lst="0623" val="89.1" />
   <dataSet lst="0700" val="87.3" />
   <dataSet lst="0701" val="87.8" />
   <dataSet lst="0702" val="89.8" />
   <dataSet lst="0703" val="89.7" />
  </stn>
  <stn stnName="슬라이딩-도착" stnNo="2554">
   <dataSet lst="0604" val="94.2" />
   <dataSet lst="0605" val="96.7" />
   <dataSet lst="0606" val="96.8" />
   <dataSet lst="0607" val="96.0" />
   <dataSet lst="0608" val="96.6" />
   <dataSet lst="0609" val="92.3" />
   <dataSet lst="0610" val="85.9" />
   <dataSet lst="0611" val="78.9" />
   <dataSet lst="0612" val="70.1" />
   <dataSet lst="0613" val="64.4" />
   <dataSet lst="0614" val="58.1" />
   <dataSet lst="0615" val="59.8" />
   <dataSet lst="0616" val="64.1" />
   <dataSet lst="0617" val="74.9" />
   <dataSet lst="0618" val="78.9" />
   <dataSet lst="0619" val="85.8" />
   <dataSet lst="0620" val="88.4" />
   <dataSet lst="0621" val="90.1" />
   <dataSet lst="0622" val="87.5" />
   <dataSet lst="0623" val="89.1" />
   <dataSet lst="0700" val="87.3" />
   <dataSet lst="0701" val="87.8" />
   <dataSet lst="0702" val="89.8" />
   <dataSet lst="0703" val="89.7" />
  </stn>
 </regionGroup>
 <regionGroup grCode="9903" grName="용평 알파인 경기장">
  <stn stnName="발왕산" stnNo="2552">
   <dataSet lst="0604" val="100.0" />
   <dataSet lst="0605" val="100.0" />
   <dataSet lst="0606" val="100.0" />
   <dataSet lst="0607" val="100.0" />
   <dataSet lst="0608" val="100.0" />
   <dataSet lst="0609" val="93.1" />
   <dataSet lst="0610" val="87.9" />
   <dataSet lst="0611" val="83.3" />
   <dataSet lst="0612" val="76.2" />
   <dataSet lst="0613" val="71.3" />
   <dataSet lst="0614" val="61.3" />
   <dataSet lst="0615" val="62.8" />
   <dataSet lst="0616" val="65.2" />
   <dataSet lst="0617" val="76.8" />
   <dataSet lst="0618" val="81.2" />
   <dataSet lst="0619" val="89.5" />
   <dataSet lst="0620" val="89.7" />
   <dataSet lst="0621" val="87.5" />
   <dataSet lst="0622" val="84.0" />
   <dataSet lst="0623" val="83.6" />
   <dataSet lst="0700" val="84.9" />
   <dataSet lst="0701" val="87.1" />
   <dataSet lst="0702" val="88.0" />
   <dataSet lst="0703" val="85.1" />
  </stn>
  <stn stnName="알파인-대회전-출발" stnNo="2560">
   <dataSet lst="0604" val="100.0" />
   <dataSet lst="0605" val="100.0" />
   <dataSet lst="0606" val="100.0" />
   <dataSet lst="0607" val="100.0" />
   <dataSet lst="0608" val="100.0" />
   <dataSet lst="0609" val="93.1" />
   <dataSet lst="0610" val="87.9" />
   <dataSet lst="0611" val="83.3" />
   <dataSet lst="0612" val="76.2" />
   <dataSet lst="0613" val="71.3" />
   <dataSet lst="0614" val="61.3" />
   <dataSet lst="0615" val="62.8" />
   <dataSet lst="0616" val="65.2" />
   <dataSet lst="0617" val="76.8" />
   <dataSet lst="0618" val="81.2" />
   <dataSet lst="0619" val="89.5" />
   <dataSet lst="0620" val="89.7" />
   <dataSet lst="0621" val="87.5" />
   <dataSet lst="0622" val="84.0" />
   <dataSet lst="0623" val="83.6" />
   <dataSet lst="0700" val="84.9" />
   <dataSet lst="0701" val="87.1" />
   <dataSet lst="0702" val="88.0" />
   <dataSet lst="0703" val="85.1" />
  </stn>
  <stn stnName="알파인-대회전-중간1" stnNo="2578">
   <dataSet lst="0604" val="98.7" />
   <dataSet lst="0605" val="99.6" />
   <dataSet lst="0606" val="99.5" />
   <dataSet lst="0607" val="100.0" />
   <dataSet lst="0608" val="100.0" />
   <dataSet lst="0609" val="94.4" />
   <dataSet lst="0610" val="85.7" />
   <dataSet lst="0611" val="80.6" />
   <dataSet lst="0612" val="73.2" />
   <dataSet lst="0613" val="68.9" />
   <dataSet lst="0614" val="58.2" />
   <dataSet lst="0615" val="63.4" />
   <dataSet lst="0616" val="65.0" />
   <dataSet lst="0617" val="77.2" />
   <dataSet lst="0618" val="81.6" />
   <dataSet lst="0619" val="90.3" />
   <dataSet lst="0620" val="90.3" />
   <dataSet lst="0621" val="88.6" />
   <dataSet lst="0622" val="86.1" />
   <dataSet lst="0623" val="85.9" />
   <dataSet lst="0700" val="86.8" />
   <dataSet lst="0701" val="88.9" />
   <dataSet lst="0702" val="90.0" />
   <dataSet lst="0703" val="86.9" />
  </stn>
  <stn stnName="알파인-대회전-중간2" stnNo="2579">
   <dataSet lst="0604" val="98.7" />
   <dataSet lst="0605" val="99.6" />
   <dataSet lst="0606" val="99.5" />
   <dataSet lst="0607" val="100.0" />
   <dataSet lst="0608" val="100.0" />
   <dataSet lst="0609" val="94.4" />
   <dataSet lst="0610" val="85.7" />
   <dataSet lst="0611" val="80.6" />
   <dataSet lst="0612" val="73.2" />
   <dataSet lst="0613" val="68.9" />
   <dataSet lst="0614" val="58.2" />
   <dataSet lst="0615" val="63.4" />
   <dataSet lst="0616" val="65.0" />
   <dataSet lst="0617" val="77.2" />
   <dataSet lst="0618" val="81.6" />
   <dataSet lst="0619" val="90.3" />
   <dataSet lst="0620" val="90.3" />
   <dataSet lst="0621" val="88.6" />
   <dataSet lst="0622" val="86.1" />
   <dataSet lst="0623" val="85.9" />
   <dataSet lst="0700" val="86.8" />
   <dataSet lst="0701" val="88.9" />
   <dataSet lst="0702" val="90.0" />
   <dataSet lst="0703" val="86.9" />
  </stn>
  <stn stnName="알파인-대회전-도착" stnNo="2561">
   <dataSet lst="0604" val="98.7" />
   <dataSet lst="0605" val="99.6" />
   <dataSet lst="0606" val="99.5" />
   <dataSet lst="0607" val="100.0" />
   <dataSet lst="0608" val="100.0" />
   <dataSet lst="0609" val="94.4" />
   <dataSet lst="0610" val="85.7" />
   <dataSet lst="0611" val="80.6" />
   <dataSet lst="0612" val="73.2" />
   <dataSet lst="0613" val="68.9" />
   <dataSet lst="0614" val="58.2" />
   <dataSet lst="0615" val="63.4" />
   <dataSet lst="0616" val="65.0" />
   <dataSet lst="0617" val="77.2" />
   <dataSet lst="0618" val="81.6" />
   <dataSet lst="0619" val="90.3" />
   <dataSet lst="0620" val="90.3" />
   <dataSet lst="0621" val="88.6" />
   <dataSet lst="0622" val="86.1" />
   <dataSet lst="0623" val="85.9" />
   <dataSet lst="0700" val="86.8" />
   <dataSet lst="0701" val="88.9" />
   <dataSet lst="0702" val="90.0" />
   <dataSet lst="0703" val="86.9" />
  </stn>
 </regionGroup>
 <regionGroup grCode="9904" grName="정선 알파인 경기장">
  <stn stnName="알파인-활강-출발" stnNo="2584">
   <dataSet lst="0604" val="100.0" />
   <dataSet lst="0605" val="98.6" />
   <dataSet lst="0606" val="100.0" />
   <dataSet lst="0607" val="100.0" />
   <dataSet lst="0608" val="100.0" />
   <dataSet lst="0609" val="95.1" />
   <dataSet lst="0610" val="85.3" />
   <dataSet lst="0611" val="78.3" />
   <dataSet lst="0612" val="77.4" />
   <dataSet lst="0613" val="76.0" />
   <dataSet lst="0614" val="73.2" />
   <dataSet lst="0615" val="72.4" />
   <dataSet lst="0616" val="78.0" />
   <dataSet lst="0617" val="83.7" />
   <dataSet lst="0618" val="79.5" />
   <dataSet lst="0619" val="79.7" />
   <dataSet lst="0620" val="85.1" />
   <dataSet lst="0621" val="81.6" />
   <dataSet lst="0622" val="79.0" />
   <dataSet lst="0623" val="84.0" />
   <dataSet lst="0700" val="83.1" />
   <dataSet lst="0701" val="80.0" />
   <dataSet lst="0702" val="76.6" />
   <dataSet lst="0703" val="72.0" />
  </stn>
  <stn stnName="알파인-슈퍼대회전-출발" stnNo="2585">
   <dataSet lst="0604" val="100.0" />
   <dataSet lst="0605" val="98.6" />
   <dataSet lst="0606" val="100.0" />
   <dataSet lst="0607" val="100.0" />
   <dataSet lst="0608" val="100.0" />
   <dataSet lst="0609" val="95.1" />
   <dataSet lst="0610" val="85.3" />
   <dataSet lst="0611" val="78.3" />
   <dataSet lst="0612" val="77.4" />
   <dataSet lst="0613" val="76.0" />
   <dataSet lst="0614" val="73.2" />
   <dataSet lst="0615" val="72.4" />
   <dataSet lst="0616" val="78.0" />
   <dataSet lst="0617" val="83.7" />
   <dataSet lst="0618" val="79.5" />
   <dataSet lst="0619" val="79.7" />
   <dataSet lst="0620" val="85.1" />
   <dataSet lst="0621" val="81.6" />
   <dataSet lst="0622" val="79.0" />
   <dataSet lst="0623" val="84.0" />
   <dataSet lst="0700" val="83.1" />
   <dataSet lst="0701" val="80.0" />
   <dataSet lst="0702" val="76.6" />
   <dataSet lst="0703" val="72.0" />
  </stn>
  <stn stnName="알파인-활강-중간" stnNo="2586">
   <dataSet lst="0604" val="100.0" />
   <dataSet lst="0605" val="98.6" />
   <dataSet lst="0606" val="100.0" />
   <dataSet lst="0607" val="100.0" />
   <dataSet lst="0608" val="100.0" />
   <dataSet lst="0609" val="95.1" />
   <dataSet lst="0610" val="85.3" />
   <dataSet lst="0611" val="78.3" />
   <dataSet lst="0612" val="77.4" />
   <dataSet lst="0613" val="76.0" />
   <dataSet lst="0614" val="73.2" />
   <dataSet lst="0615" val="72.4" />
   <dataSet lst="0616" val="78.0" />
   <dataSet lst="0617" val="83.7" />
   <dataSet lst="0618" val="79.5" />
   <dataSet lst="0619" val="79.7" />
   <dataSet lst="0620" val="85.1" />
   <dataSet lst="0621" val="81.6" />
   <dataSet lst="0622" val="79.0" />
   <dataSet lst="0623" val="84.0" />
   <dataSet lst="0700" val="83.1" />
   <dataSet lst="0701" val="80.0" />
   <dataSet lst="0702" val="76.6" />
   <dataSet lst="0703" val="72.0" />
  </stn>
  <stn stnName="알파인-활강-도착" stnNo="2587">
   <dataSet lst="0604" val="93.0" />
   <dataSet lst="0605" val="89.4" />
   <dataSet lst="0606" val="94.4" />
   <dataSet lst="0607" val="95.3" />
   <dataSet lst="0608" val="95.3" />
   <dataSet lst="0609" val="88.6" />
   <dataSet lst="0610" val="79.1" />
   <dataSet lst="0611" val="68.9" />
   <dataSet lst="0612" val="67.7" />
   <dataSet lst="0613" val="66.8" />
   <dataSet lst="0614" val="65.9" />
   <dataSet lst="0615" val="64.5" />
   <dataSet lst="0616" val="72.7" />
   <dataSet lst="0617" val="73.7" />
   <dataSet lst="0618" val="71.4" />
   <dataSet lst="0619" val="74.0" />
   <dataSet lst="0620" val="77.8" />
   <dataSet lst="0621" val="86.2" />
   <dataSet lst="0622" val="86.5" />
   <dataSet lst="0623" val="88.7" />
   <dataSet lst="0700" val="87.1" />
   <dataSet lst="0701" val="89.6" />
   <dataSet lst="0702" val="89.3" />
   <dataSet lst="0703" val="89.7" />
  </stn>
  <stn stnName="정선경기장-하부" stnNo="2571">
   <dataSet lst="0604" val="91.6" />
   <dataSet lst="0605" val="91.9" />
   <dataSet lst="0606" val="93.0" />
   <dataSet lst="0607" val="92.5" />
   <dataSet lst="0608" val="90.8" />
   <dataSet lst="0609" val="85.7" />
   <dataSet lst="0610" val="78.1" />
   <dataSet lst="0611" val="68.3" />
   <dataSet lst="0612" val="62.0" />
   <dataSet lst="0613" val="58.3" />
   <dataSet lst="0614" val="59.2" />
   <dataSet lst="0615" val="59.5" />
   <dataSet lst="0616" val="64.0" />
   <dataSet lst="0617" val="75.3" />
   <dataSet lst="0618" val="75.2" />
   <dataSet lst="0619" val="77.5" />
   <dataSet lst="0620" val="79.3" />
   <dataSet lst="0621" val="80.7" />
   <dataSet lst="0622" val="79.9" />
   <dataSet lst="0623" val="85.4" />
   <dataSet lst="0700" val="88.6" />
   <dataSet lst="0701" val="90.9" />
   <dataSet lst="0702" val="93.2" />
   <dataSet lst="0703" val="89.2" />
  </stn>
 </regionGroup>
 <regionGroup grCode="9905" grName="보광 스노 경기장">
  <stn stnName="태기산" stnNo="2570">
   <dataSet lst="0604" val="98.8" />
   <dataSet lst="0605" val="97.6" />
   <dataSet lst="0606" val="96.4" />
   <dataSet lst="0607" val="96.5" />
   <dataSet lst="0608" val="96.4" />
   <dataSet lst="0609" val="92.0" />
   <dataSet lst="0610" val="85.7" />
   <dataSet lst="0611" val="75.4" />
   <dataSet lst="0612" val="67.4" />
   <dataSet lst="0613" val="65.9" />
   <dataSet lst="0614" val="65.7" />
   <dataSet lst="0615" val="66.9" />
   <dataSet lst="0616" val="72.5" />
   <dataSet lst="0617" val="82.7" />
   <dataSet lst="0618" val="82.9" />
   <dataSet lst="0619" val="86.3" />
   <dataSet lst="0620" val="90.6" />
   <dataSet lst="0621" val="91.3" />
   <dataSet lst="0622" val="94.4" />
   <dataSet lst="0623" val="91.1" />
   <dataSet lst="0700" val="94.0" />
   <dataSet lst="0701" val="98.9" />
   <dataSet lst="0702" val="100.0" />
   <dataSet lst="0703" val="99.2" />
  </stn>
  <stn stnName="크로스-출발" stnNo="2580">
   <dataSet lst="0604" val="100.0" />
   <dataSet lst="0605" val="100.0" />
   <dataSet lst="0606" val="99.2" />
   <dataSet lst="0607" val="100.0" />
   <dataSet lst="0608" val="100.0" />
   <dataSet lst="0609" val="96.4" />
   <dataSet lst="0610" val="91.8" />
   <dataSet lst="0611" val="83.6" />
   <dataSet lst="0612" val="73.5" />
   <dataSet lst="0613" val="69.8" />
   <dataSet lst="0614" val="71.4" />
   <dataSet lst="0615" val="71.8" />
   <dataSet lst="0616" val="79.1" />
   <dataSet lst="0617" val="88.2" />
   <dataSet lst="0618" val="87.3" />
   <dataSet lst="0619" val="89.2" />
   <dataSet lst="0620" val="92.4" />
   <dataSet lst="0621" val="92.5" />
   <dataSet lst="0622" val="94.2" />
   <dataSet lst="0623" val="92.8" />
   <dataSet lst="0700" val="94.3" />
   <dataSet lst="0701" val="97.0" />
   <dataSet lst="0702" val="97.9" />
   <dataSet lst="0703" val="95.1" />
  </stn>
  <stn stnName="크로스-도착" stnNo="2581">
   <dataSet lst="0604" val="99.1" />
   <dataSet lst="0605" val="96.5" />
   <dataSet lst="0606" val="96.6" />
   <dataSet lst="0607" val="99.2" />
   <dataSet lst="0608" val="99.9" />
   <dataSet lst="0609" val="95.3" />
   <dataSet lst="0610" val="85.7" />
   <dataSet lst="0611" val="74.9" />
   <dataSet lst="0612" val="68.5" />
   <dataSet lst="0613" val="68.6" />
   <dataSet lst="0614" val="66.5" />
   <dataSet lst="0615" val="68.5" />
   <dataSet lst="0616" val="74.5" />
   <dataSet lst="0617" val="82.5" />
   <dataSet lst="0618" val="77.5" />
   <dataSet lst="0619" val="79.2" />
   <dataSet lst="0620" val="87.6" />
   <dataSet lst="0621" val="87.2" />
   <dataSet lst="0622" val="91.6" />
   <dataSet lst="0623" val="89.0" />
   <dataSet lst="0700" val="95.2" />
   <dataSet lst="0701" val="99.6" />
   <dataSet lst="0702" val="100.0" />
   <dataSet lst="0703" val="93.0" />
  </stn>
  <stn stnName="슬로프스타일-출발" stnNo="2588">
   <dataSet lst="0604" val="98.9" />
   <dataSet lst="0605" val="96.7" />
   <dataSet lst="0606" val="96.4" />
   <dataSet lst="0607" val="97.8" />
   <dataSet lst="0608" val="98.6" />
   <dataSet lst="0609" val="94.5" />
   <dataSet lst="0610" val="85.6" />
   <dataSet lst="0611" val="73.5" />
   <dataSet lst="0612" val="68.1" />
   <dataSet lst="0613" val="67.6" />
   <dataSet lst="0614" val="66.6" />
   <dataSet lst="0615" val="66.4" />
   <dataSet lst="0616" val="72.1" />
   <dataSet lst="0617" val="81.5" />
   <dataSet lst="0618" val="77.2" />
   <dataSet lst="0619" val="80.0" />
   <dataSet lst="0620" val="87.7" />
   <dataSet lst="0621" val="87.6" />
   <dataSet lst="0622" val="92.0" />
   <dataSet lst="0623" val="89.7" />
   <dataSet lst="0700" val="95.2" />
   <dataSet lst="0701" val="100.0" />
   <dataSet lst="0702" val="100.0" />
   <dataSet lst="0703" val="95.4" />
  </stn>
  <stn stnName="모글-출발" stnNo="2582">
   <dataSet lst="0604" val="99.1" />
   <dataSet lst="0605" val="96.5" />
   <dataSet lst="0606" val="96.6" />
   <dataSet lst="0607" val="99.2" />
   <dataSet lst="0608" val="99.9" />
   <dataSet lst="0609" val="95.3" />
   <dataSet lst="0610" val="85.7" />
   <dataSet lst="0611" val="74.9" />
   <dataSet lst="0612" val="68.5" />
   <dataSet lst="0613" val="68.6" />
   <dataSet lst="0614" val="66.5" />
   <dataSet lst="0615" val="68.5" />
   <dataSet lst="0616" val="74.5" />
   <dataSet lst="0617" val="82.5" />
   <dataSet lst="0618" val="77.5" />
   <dataSet lst="0619" val="79.2" />
   <dataSet lst="0620" val="87.6" />
   <dataSet lst="0621" val="87.2" />
   <dataSet lst="0622" val="91.6" />
   <dataSet lst="0623" val="89.0" />
   <dataSet lst="0700" val="95.2" />
   <dataSet lst="0701" val="99.6" />
   <dataSet lst="0702" val="100.0" />
   <dataSet lst="0703" val="93.0" />
  </stn>
  <stn stnName="슬로프스타일-도착" stnNo="2583">
   <dataSet lst="0604" val="99.1" />
   <dataSet lst="0605" val="96.5" />
   <dataSet lst="0606" val="96.6" />
   <dataSet lst="0607" val="99.2" />
   <dataSet lst="0608" val="99.9" />
   <dataSet lst="0609" val="95.3" />
   <dataSet lst="0610" val="85.7" />
   <dataSet lst="0611" val="74.9" />
   <dataSet lst="0612" val="68.5" />
   <dataSet lst="0613" val="68.6" />
   <dataSet lst="0614" val="66.5" />
   <dataSet lst="0615" val="68.5" />
   <dataSet lst="0616" val="74.5" />
   <dataSet lst="0617" val="82.5" />
   <dataSet lst="0618" val="77.5" />
   <dataSet lst="0619" val="79.2" />
   <dataSet lst="0620" val="87.6" />
   <dataSet lst="0621" val="87.2" />
   <dataSet lst="0622" val="91.6" />
   <dataSet lst="0623" val="89.0" />
   <dataSet lst="0700" val="95.2" />
   <dataSet lst="0701" val="99.6" />
   <dataSet lst="0702" val="100.0" />
   <dataSet lst="0703" val="93.0" />
  </stn>
 </regionGroup>
 <regionGroup grCode="9906" grName="평창 올림픽 스타디움">
  <stn stnName="평창-올림픽-스타디움" stnNo="47100">
   <dataSet lst="0604" val="95.2" />
   <dataSet lst="0605" val="95.6" />
   <dataSet lst="0606" val="97.2" />
   <dataSet lst="0607" val="97.7" />
   <dataSet lst="0608" val="97.9" />
   <dataSet lst="0609" val="93.1" />
   <dataSet lst="0610" val="89.2" />
   <dataSet lst="0611" val="83.0" />
   <dataSet lst="0612" val="78.0" />
   <dataSet lst="0613" val="72.9" />
   <dataSet lst="0614" val="70.2" />
   <dataSet lst="0615" val="68.1" />
   <dataSet lst="0616" val="74.7" />
   <dataSet lst="0617" val="77.7" />
   <dataSet lst="0618" val="78.1" />
   <dataSet lst="0619" val="84.6" />
   <dataSet lst="0620" val="89.3" />
   <dataSet lst="0621" val="89.8" />
   <dataSet lst="0622" val="88.5" />
   <dataSet lst="0623" val="85.6" />
   <dataSet lst="0700" val="87.8" />
   <dataSet lst="0701" val="85.3" />
   <dataSet lst="0702" val="83.4" />
   <dataSet lst="0703" val="86.7" />
  </stn>
  <stn stnName="강릉" stnNo="47105">
   <dataSet lst="0604" val="91.1" />
   <dataSet lst="0605" val="89.9" />
   <dataSet lst="0606" val="90.6" />
   <dataSet lst="0607" val="88.0" />
   <dataSet lst="0608" val="85.5" />
   <dataSet lst="0609" val="81.6" />
   <dataSet lst="0610" val="76.0" />
   <dataSet lst="0611" val="68.8" />
   <dataSet lst="0612" val="67.2" />
   <dataSet lst="0613" val="63.1" />
   <dataSet lst="0614" val="60.8" />
   <dataSet lst="0615" val="61.5" />
   <dataSet lst="0616" val="67.3" />
   <dataSet lst="0617" val="83.0" />
   <dataSet lst="0618" val="83.7" />
   <dataSet lst="0619" val="74.2" />
   <dataSet lst="0620" val="72.0" />
   <dataSet lst="0621" val="70.9" />
   <dataSet lst="0622" val="67.2" />
   <dataSet lst="0623" val="64.4" />
   <dataSet lst="0700" val="61.6" />
   <dataSet lst="0701" val="61.0" />
   <dataSet lst="0702" val="60.4" />
   <dataSet lst="0703" val="61.5" />
  </stn>
 </regionGroup>
</REH>

